xldt.cpython-39-darwin.so
xldt-0.3.0.dist-info/LICENSE
xldt-0.3.0.dist-info/METADATA
xldt-0.3.0.dist-info/WHEEL
xldt-0.3.0.dist-info/top_level.txt
xldt-0.3.0.dist-info/RECORD
