Metadata-Version: 2.1
Name: xldt
Version: 0.3.0
Summary: Excel-compatible date and time functions.
Home-page: https://github.com/vtudorache/xldt
Author: Vlad Tudorache
Author-email: tudorache.vlad@gmail.com
License: UNKNOWN
Keywords: python excel date time
Platform: UNKNOWN
Classifier: Programming Language :: C
Classifier: License :: OSI Approved :: MIT License
Requires-Python: >=3.6
License-File: LICENSE
